euppbench_datasets/__init__.py
euppbench_datasets/catalog/catalog.yml
euppbench_datasets/catalog/euppbench/catalog.yml
euppbench_datasets/catalog/euppbench/training_data/catalog.yml
euppbench_datasets/catalog/euppbench/training_data/gridded/catalog.yml
euppbench_datasets/catalog/euppbench/training_data/stations/catalog.yml
euppbench_datasets/catalog/euppbench/training_data/stations/austria/catalog.yml
euppbench_datasets/catalog/euppbench/training_data/stations/belgium/catalog.yml
euppbench_datasets/catalog/euppbench/training_data/stations/france/catalog.yml
euppbench_datasets/catalog/euppbench/training_data/stations/germany/catalog.yml
euppbench_datasets/catalog/euppbench/training_data/stations/netherlands/catalog.yml
euppbench_datasets/catalog/euprecipbench/catalog.yml
euppbench_datasets-0.2.4.dist-info/licenses/LICENSE
euppbench_datasets-0.2.4.dist-info/METADATA
euppbench_datasets-0.2.4.dist-info/WHEEL
euppbench_datasets-0.2.4.dist-info/top_level.txt
euppbench_datasets-0.2.4.dist-info/RECORD
