Metadata-Version: 2.4
Name: euppbench-datasets
Version: 0.2.4
Summary: Intake catalogue for the EUPPBench postprocessing datasets
Author-email: Jonathan Demaeyer <jodemaey@meteo.be>
License: BSD 3-Clause License
Project-URL: homepage, https://github.com/EUPP-benchmark/intake-eumetnet-postprocessing-benchmark
Project-URL: documentation, https://eupp-benchmark.github.io/EUPPBench-doc/
Keywords: meteorology,postprocessing,meteorological-data
Classifier: Programming Language :: Python
Classifier: Programming Language :: Python :: 3
Classifier: Programming Language :: Python :: 3.10
Classifier: Programming Language :: Python :: 3.11
Classifier: Programming Language :: Python :: 3.12
Classifier: Operating System :: OS Independent
Classifier: Development Status :: 5 - Production/Stable
Classifier: Intended Audience :: Science/Research
Classifier: Topic :: Scientific/Engineering :: Atmospheric Science
Requires-Python: >=3.10
License-File: LICENSE
Requires-Dist: intake>=2.0.8
Requires-Dist: intake-xarray
Requires-Dist: ipykernel>=6.29.5
Requires-Dist: jinja2>=3.1.6
Requires-Dist: s3fs>=2025.0.0
Requires-Dist: pytest
Dynamic: license-file
